cobalt/__init__.py
cobalt/akn.py
cobalt/amendment.py
cobalt/collection.py
cobalt/debate.py
cobalt/hierarchical.py
cobalt/judgment.py
cobalt/openstructure.py
cobalt/portion.py
cobalt/schemas.py
cobalt/uri.py
cobalt/xsd/akomantoso30-lenient.xsd
cobalt/xsd/akomantoso30.xsd
cobalt/xsd/xml.xsd
cobalt-9.0.1.dist-info/LICENSE
cobalt-9.0.1.dist-info/METADATA
cobalt-9.0.1.dist-info/WHEEL
cobalt-9.0.1.dist-info/top_level.txt
cobalt-9.0.1.dist-info/RECORD
